phonenumberfmt/__init__.py
phonenumberfmt/country.py
phonenumberfmt/format_phone_number.py
phonenumberfmt/format_phone_number_list.py
py_phone_number_fmt-2.0.2.dist-info/licenses/LICENSE
tests/__init__.py
tests/test_format_phone_number.py
tests/test_format_phone_number_list.py
py_phone_number_fmt-2.0.2.dist-info/METADATA
py_phone_number_fmt-2.0.2.dist-info/WHEEL
py_phone_number_fmt-2.0.2.dist-info/top_level.txt
py_phone_number_fmt-2.0.2.dist-info/RECORD
