Metadata-Version: 2.4
Name: py-phone-number-fmt
Version: 2.0.2
Summary: Sanitize, validate and format phone numbers into E.164 valid phone numbers.
Home-page: https://github.com/SectorLabs/py-phone-number-fmt
Author: Sector Labs
Author-email: open-source@sectorlabs.ro
License: MIT License
Keywords: phone number,phone,formatting,validation
Classifier: Intended Audience :: Developers
Classifier: License :: OSI Approved :: MIT License
Classifier: Operating System :: OS Independent
Classifier: Programming Language :: Python
Classifier: Programming Language :: Python :: 3.7
Classifier: Programming Language :: Python :: 3.8
Classifier: Programming Language :: Python :: 3.9
License-File: LICENSE
Requires-Dist: phonenumbers<=9.0.18,>=8.13.33
Dynamic: author
Dynamic: author-email
Dynamic: classifier
Dynamic: description
Dynamic: description-content-type
Dynamic: home-page
Dynamic: keywords
Dynamic: license
Dynamic: license-file
Dynamic: requires-dist
Dynamic: summary
